rfd/__init__.py
rfd/ai_validator.py
rfd/analyze.py
rfd/auto_handoff.py
rfd/build.py
rfd/claude_integration.py
rfd/cli.py
rfd/cli_clean.py
rfd/cli_enforcement.py
rfd/cli_prevent.py
rfd/cli_utils.py
rfd/config_manager.py
rfd/context_manager.py
rfd/database_accountability.py
rfd/db_utils.py
rfd/enforcement.py
rfd/feature_commands.py
rfd/feature_manager.py
rfd/init_wizard.py
rfd/migration.py
rfd/prevention.py
rfd/project_updater.py
rfd/rfd.py
rfd/session.py
rfd/spec.py
rfd/spec_formatter.py
rfd/spec_generator.py
rfd/speckit_integration.py
rfd/status_commands.py
rfd/template_sync.py
rfd/update_check.py
rfd/validation.py
rfd/workflow_engine.py
rfd/workflow_isolation.py
rfd/templates/CLAUDE.md
rfd/templates/PROJECT.md
rfd/templates/commands/rfd-analyze.md
rfd/templates/commands/rfd-build.md
rfd/templates/commands/rfd-check.md
rfd/templates/commands/rfd-complete.md
rfd/templates/commands/rfd-dashboard.md
rfd/templates/commands/rfd-features.md
rfd/templates/commands/rfd-fix.md
rfd/templates/commands/rfd-gaps.md
rfd/templates/commands/rfd-help.md
rfd/templates/commands/rfd-init.md
rfd/templates/commands/rfd-plan.md
rfd/templates/commands/rfd-quick-ref.md
rfd/templates/commands/rfd-resume.md
rfd/templates/commands/rfd-session.md
rfd/templates/commands/rfd-setup.md
rfd/templates/commands/rfd-spec.md
rfd/templates/commands/rfd-start.md
rfd/templates/commands/rfd-validate.md
rfd/templates/commands/rfd-workflow-guide.md
rfd/templates/commands/rfd.md
rfd_protocol-5.5.1.dist-info/METADATA
rfd_protocol-5.5.1.dist-info/WHEEL
rfd_protocol-5.5.1.dist-info/entry_points.txt
rfd_protocol-5.5.1.dist-info/top_level.txt
rfd_protocol-5.5.1.dist-info/RECORD
