Metadata-Version: 2.4
Name: rfd-protocol
Version: 5.5.1
Summary: Reality-First Development Protocol - Prevents AI hallucination and ensures spec-driven development
Home-page: https://github.com/rfd-protocol/rfd
Author: RFD Protocol Team
Author-email: RFD Protocol Team <team@rfd-protocol.dev>
Maintainer-email: RFD Protocol Team <team@rfd-protocol.dev>
License: MIT
Project-URL: Homepage, https://github.com/rfd-protocol/rfd
Project-URL: Repository, https://github.com/rfd-protocol/rfd
Project-URL: Documentation, https://github.com/rfd-protocol/rfd/docs
Classifier: Development Status :: 4 - Beta
Classifier: Intended Audience :: Developers
Classifier: License :: OSI Approved :: MIT License
Classifier: Operating System :: OS Independent
Classifier: Programming Language :: Python :: 3
Classifier: Programming Language :: Python :: 3.8
Classifier: Programming Language :: Python :: 3.9
Classifier: Programming Language :: Python :: 3.10
Classifier: Programming Language :: Python :: 3.11
Classifier: Programming Language :: Python :: 3.12
Classifier: Topic :: Software Development :: Quality Assurance
Classifier: Topic :: Software Development :: Testing
Classifier: Topic :: Software Development :: Build Tools
Requires-Python: >=3.8
Requires-Dist: click>=8.0.0
Requires-Dist: requests>=2.28.0
Requires-Dist: pyyaml>=6.0
Requires-Dist: questionary>=1.10.0
Requires-Dist: python-frontmatter>=1.0.0
Requires-Dist: packaging>=21.0
Requires-Dist: tomli>=1.2.0; python_version < "3.11"
Provides-Extra: dev
Requires-Dist: pytest>=7.4.0; extra == "dev"
Requires-Dist: pytest-cov>=4.1.0; extra == "dev"
Requires-Dist: pytest-xdist>=3.5.0; extra == "dev"
Requires-Dist: pytest-mock>=3.12.0; extra == "dev"
Requires-Dist: pytest-timeout>=2.2.0; extra == "dev"
Requires-Dist: black>=23.12.0; extra == "dev"
Requires-Dist: ruff>=0.1.9; extra == "dev"
Requires-Dist: mypy>=1.8.0; extra == "dev"
Requires-Dist: pre-commit>=2.20.0; extra == "dev"
Requires-Dist: python-semantic-release>=8.7.0; extra == "dev"
Requires-Dist: tox>=4.11.0; extra == "dev"
Requires-Dist: coverage[toml]>=7.4.0; extra == "dev"
Provides-Extra: test
Requires-Dist: pytest>=7.4.0; extra == "test"
Requires-Dist: pytest-cov>=4.1.0; extra == "test"
Requires-Dist: pytest-timeout>=2.2.0; extra == "test"
Requires-Dist: coverage[toml]>=7.4.0; extra == "test"
Provides-Extra: docs
Requires-Dist: mkdocs>=1.5.3; extra == "docs"
Requires-Dist: mkdocs-material>=9.5.0; extra == "docs"
Requires-Dist: mkdocstrings[python]>=0.24.0; extra == "docs"
Dynamic: author
Dynamic: home-page
Dynamic: requires-python
